retriable_kafka_client/__init__.py
retriable_kafka_client/config.py
retriable_kafka_client/consumer.py
retriable_kafka_client/consumer_tracking.py
retriable_kafka_client/kafka_settings.py
retriable_kafka_client/kafka_utils.py
retriable_kafka_client/orchestrate.py
retriable_kafka_client/producer.py
retriable_kafka_client/retry_utils.py
retriable_kafka_client-0.2.0.dist-info/licenses/LICENSE
retriable_kafka_client-0.2.0.dist-info/METADATA
retriable_kafka_client-0.2.0.dist-info/WHEEL
retriable_kafka_client-0.2.0.dist-info/top_level.txt
retriable_kafka_client-0.2.0.dist-info/RECORD
