Metadata-Version: 2.4
Name: retriable-kafka-client
Version: 0.2.0
Summary: Kafka client library based on confluent-kafka with retry functionality
Author-email: Marek Szymutko <mszymutk@redhat.com>
Requires-Python: >=3.13
License-File: LICENSE
Requires-Dist: confluent-kafka>=2.12.2
Requires-Dist: pylint>=4.0.4
Dynamic: license-file
